Workbook

Sheet Read Me
A1: IT General Controls (ITGC) Testing Workbook
A2: Portfolio project by Bhuvaneshwari Kundla, September 2026
A4: Client | B4: Harbourline Payments Ltd, a FICTIONAL Dublin-based payment institution offering a SaaS payments and billing platform. All names, people and data are invented for learning purposes.
A5: Engagement | B5: Simulated IT audit testing of key IT general controls (ITGCs) supporting the systems behind financial reporting.
A6: Period tested | B6: 1 January 2026 to 30 June 2026
A7: Controls tested | B7: 6 key controls across three ITGC domains: Access to programs and data (AC), Program change (CM), Computer operations (OP).
A8: Approach | B8: 1) Walkthrough to confirm each control is designed properly. 2) Sample-based testing to confirm it operated throughout the period. 3) Exceptions evaluated, rated and reported with recommendations.
A10: Sheet guide
A11: Summary | B11: Headline results, calculated automatically from the test sheets.
A12: Scope | B12: Company background and the systems in scope.
A13: Control Matrix | B13: The 6 controls: what they do, who owns them, how they were tested and the conclusion.
A14: Sampling Guide | B14: How sample sizes were chosen.
A15: AC-01 ... OP-02 | B15: One test sheet per control, showing each sample and the result.
A16: Exceptions | B16: Findings, risk rating, recommendations and (simulated) management responses.
A17: Framework Mapping | B17: How each control links to ISO 27001:2022, DORA and SOC 2.
A19: Legend
A20: Blue text | B20: Evidence values entered from (simulated) client records
A21: Black bold text | B21: Formulas: test results are calculated, not typed
A22: Pass | B22: Sample met every test attribute
A23: Exception | B23: Sample failed at least one attribute; see Exceptions sheet

Sheet Summary
A1: Results Summary
A2: All figures below are formulas linked to the Control Matrix.
A3: Measure | B3: Result
A4: Controls tested | B4: =COUNTA('Control Matrix'!A5:A10) -> 6
A5: Controls effective | B5: =COUNTIF('Control Matrix'!M5:M10,"Effective") -> 4
A6: Controls with exceptions | B6: =COUNTIF('Control Matrix'!M5:M10,"Exception noted") -> 2
A7: Total samples tested | B7: =SUM('Control Matrix'!J5:J10) -> 60
A8: Total exceptions | B8: =SUM('Control Matrix'!L5:L10) -> 2
A9: Exception rate | B9: =IF(B7=0,0,B8/B7) -> 0.033333333
A11: Overall conclusion
B12: Key ITGCs over LedgerCore were designed appropriately and operated effectively during the period, except for one late leaver removal (EX-01) and one emergency change deployed before approval (EX-02). Both are rated Medium, and no evidence was found that either weakness was exploited.

Sheet Scope
A1: Scope and Systems
A3: Company | B3: Harbourline Payments Ltd (fictional). Approx. 180 staff, Dublin HQ. Payment institution serving small and medium businesses in Ireland and the UK.
A4: Why ITGCs matter | B4: Financial figures (fees, settlements, refunds) are calculated by the systems below. If access, changes or operations are not controlled, the numbers those systems produce cannot be trusted.
A5: Regulatory context | B5: As a payment institution, Harbourline is a financial entity within the scope of DORA, so ICT risk controls such as access management, change management and backups are also regulatory expectations.
A7: System | B7: Purpose | C7: Hosting | D7: Why in scope
A8: LedgerCore | B8: In-house payments and billing application: fees, settlements, refunds, invoicing | C8: Cloud (AWS) | D8: Generates the revenue and settlement figures used in financial reporting
A9: LedgerCore production database (PostgreSQL) | B9: Stores all transaction and customer billing data | C9: Cloud (AWS) | D9: Direct changes to data could alter reported figures
A10: CI/CD deployment pipeline | B10: Builds and releases code changes to production | C10: Cloud (AWS) | D10: Controls how changes reach the financial system
A12: Out of scope | B12: Physical and network security, end-user devices, and third-party SaaS tools (e.g., HR and ticketing platforms). In a real engagement, controls at these service providers would be covered by reviewing their own SOC reports.

Sheet Control Matrix
A1: Control Matrix
A2: Exceptions and conclusions are calculated from each test sheet.
A4: Control ID | B4: ITGC domain | C4: Control objective | D4: Control description | E4: Owner | F4: Frequency | G4: Type | H4: Nature | I4: Population | J4: Sample size | K4: How it was tested | L4: Exceptions | M4: Conclusion
A5: AC-01 | B5: Access to programs & data | C5: Only current staff can access financial systems | D5: Leaver access to LedgerCore and the production database is removed within 1 business day of termination. | E5: IT Service Desk Lead | F5: Event-driven | G5: Preventive | H5: Manual | I5: 18 | J5: 10 | K5: Inspect HR leaver report, access removal tickets and system logs. | L5: =COUNTIF('AC-01 Leavers'!J9:J18,"Exception") -> 1 | M5: =IF(L5=0,"Effective","Exception noted") -> Exception noted
A6: AC-02 | B6: Access to programs & data | C6: Access stays appropriate over time, especially privileged access | D6: Quarterly review of all user and privileged accounts by the system owner; inappropriate access removed within 5 business days. | E6: Head of Payments Ops | F6: Quarterly | G6: Detective | H6: Manual | I6: 2 | J6: 2 | K6: Inspect signed reviews, agree user list to system extract, trace removals. | L6: =COUNTIF('AC-02 Access Review'!K9:K10,"Exception") -> 0 | M6: =IF(L6=0,"Effective","Exception noted") -> Effective
A7: CM-01 | B7: Program change | C7: Only tested, approved changes reach production | D7: Changes are tested in UAT and approved by CAB before deployment; emergency changes need prior CTO approval. | E7: Change Manager | F7: Event-driven | G7: Preventive | H7: Manual | I7: 60 | J7: 15 | K7: Inspect tickets for UAT evidence and compare approval date with deployment date. | L7: =COUNTIF('CM-01 Changes'!I9:I23,"Exception") -> 1 | M7: =IF(L7=0,"Effective","Exception noted") -> Exception noted
A8: CM-02 | B8: Program change | C8: Developers cannot push their own code live | D8: Only Release/DevOps staff can deploy; the pipeline enforces a second approver. | E8: Release Manager | F8: Continuous | G8: Preventive | H8: Automated | I8: 6 | J8: 6 | K8: Inspect pipeline permissions against HR roles; inspect pipeline approval setting. | L8: =COUNTIF('CM-02 SoD'!F9:F14,"Exception") -> 0 | M8: =IF(L8=0,"Effective","Exception noted") -> Effective
A9: OP-01 | B9: Computer operations | C9: Financial data can be recovered if lost | D9: Daily automated backups; failures are alerted, ticketed and re-run within 24 hours. | E9: Infrastructure Lead | F9: Daily | G9: Detective | H9: Automated with manual follow-up | I9: 181 | J9: 25 | K9: Inspect backup job history; for failures, inspect alert, ticket and re-run. | L9: =COUNTIF('OP-01 Backups'!F9:F33,"Exception") -> 0 | M9: =IF(L9=0,"Effective","Exception noted") -> Effective
A10: OP-02 | B10: Computer operations | C10: Backups actually work when needed | D10: Quarterly restore test to a test environment, with integrity check and timing against the 4-hour RTO. | E10: Infrastructure Lead | F10: Quarterly | G10: Detective | H10: Manual | I10: 2 | J10: 2 | K10: Inspect restore test records and compare restore time to RTO. | L10: =COUNTIF('OP-02 Restore Tests'!I9:I10,"Exception") -> 0 | M10: =IF(L10=0,"Effective","Exception noted") -> Effective

Sheet Sampling Guide
A1: Sampling Guide
A2: Illustrative ranges based on common audit practice. Each firm applies its own methodology.
A4: Control frequency | B4: Typical sample size | C4: Used in this project
A5: Annual | B5: 1 | C5: -
A6: Quarterly | B6: 2 | C6: AC-02, OP-02: both quarters tested
A7: Monthly | B7: 2 to 5 | C7: -
A8: Weekly | B8: 5 to 15 | C8: -
A9: Daily | B9: 20 to 40 | C9: OP-01: 25 days
A10: Event-driven (many times a year) | B10: Depends on population size, often 25 or more | C10: AC-01: 10 of 18 leavers; CM-01: 15 of 60 changes (smaller samples chosen for this learning project)
A11: Automated / continuous | B11: Test of one, if IT general controls are effective | C11: CM-02: all 6 accounts plus pipeline setting
A13: Key idea | B13: Auditors test a sample rather than every item. If the sample has no exceptions, they can reasonably conclude the control worked across the whole period.

Sheet AC-01 Leavers
A1: AC-01 Timely removal of leaver access
A3: Control | B3: HR's leaver report triggers a Service Desk ticket. Access to LedgerCore and the production database is removed within 1 business day of the termination date.
A4: Population | B4: 18 leavers between 1 Jan and 30 Jun 2026 (per HR leaver report). Completeness checked by agreeing the report to the payroll leaver list.
A5: Sample | B5: 10 leavers selected at random.
A6: Test attributes | B6: A) Access removed from every system the leaver held. B) Removal within 1 business day of termination. C) Where late, check system logs for any log-ins after termination.
A8: # | B8: Employee ID | C8: Department | D8: Termination date | E8: LedgerCore access removed | F8: Database access removed | G8: Latest removal date | H8: Business days to removal | I8: Log-ins after termination | J8: Result
A9: 1 | B9: E1042 | C9: Finance | D9: 46038 | E9: 46038 | F9: No access held | G9: =MAX(E9:F9) -> 46038 | H9: =NETWORKDAYS(D9,G9)-1 -> 0 | I9: 0 | J9: =IF(H9<=1,"Pass","Exception") -> Pass
A10: 2 | B10: E1108 | C10: Engineering | D10: 46052 | E10: 46052 | F10: 46052 | G10: =MAX(E10:F10) -> 46052 | H10: =NETWORKDAYS(D10,G10)-1 -> 0 | I10: 0 | J10: =IF(H10<=1,"Pass","Exception") -> Pass
A11: 3 | B11: E1077 | C11: Customer Operations | D11: 46066 | E11: 46069 | F11: No access held | G11: =MAX(E11:F11) -> 46069 | H11: =NETWORKDAYS(D11,G11)-1 -> 1 | I11: 0 | J11: =IF(H11<=1,"Pass","Exception") -> Pass
A12: 4 | B12: E1150 | C12: Engineering | D12: 46080 | E12: 46080 | F12: 46083 | G12: =MAX(E12:F12) -> 46083 | H12: =NETWORKDAYS(D12,G12)-1 -> 1 | I12: 0 | J12: =IF(H12<=1,"Pass","Exception") -> Pass
A13: 5 | B13: E1019 | C13: Sales | D13: 46094 | E13: 46106 | F13: No access held | G13: =MAX(E13:F13) -> 46106 | H13: =NETWORKDAYS(D13,G13)-1 -> 8 | I13: 0 | J13: =IF(H13<=1,"Pass","Exception") -> Exception
A14: 6 | B14: E1163 | C14: Risk & Compliance | D14: 46112 | E14: 46112 | F14: No access held | G14: =MAX(E14:F14) -> 46112 | H14: =NETWORKDAYS(D14,G14)-1 -> 0 | I14: 0 | J14: =IF(H14<=1,"Pass","Exception") -> Pass
A15: 7 | B15: E1091 | C15: Customer Operations | D15: 46129 | E15: 46129 | F15: No access held | G15: =MAX(E15:F15) -> 46129 | H15: =NETWORKDAYS(D15,G15)-1 -> 0 | I15: 0 | J15: =IF(H15<=1,"Pass","Exception") -> Pass
A16: 8 | B16: E1134 | C16: Engineering | D16: 46157 | E16: 46157 | F16: 46157 | G16: =MAX(E16:F16) -> 46157 | H16: =NETWORKDAYS(D16,G16)-1 -> 0 | I16: 0 | J16: =IF(H16<=1,"Pass","Exception") -> Pass
A17: 9 | B17: E1177 | C17: Finance | D17: 46171 | E17: 46174 | F17: No access held | G17: =MAX(E17:F17) -> 46174 | H17: =NETWORKDAYS(D17,G17)-1 -> 1 | I17: 0 | J17: =IF(H17<=1,"Pass","Exception") -> Pass
A18: 10 | B18: E1056 | C18: Marketing | D18: 46199 | E18: 46199 | F18: No access held | G18: =MAX(E18:F18) -> 46199 | H18: =NETWORKDAYS(D18,G18)-1 -> 0 | I18: 0 | J18: =IF(H18<=1,"Pass","Exception") -> Pass
A20: Note: E1019 access removed 8 business days after termination (see Exceptions, EX-01). Logs show no log-ins after termination.

Sheet AC-02 Access Review
A1: AC-02 Quarterly user access review (including privileged accounts)
A3: Control | B3: Each quarter the LedgerCore system owner reviews all user and privileged accounts. The review is completed within 15 days of quarter end, and inappropriate access is removed within 5 business days of sign-off.
A4: Population | B4: 2 quarterly reviews covering the period (Q1 and Q2 2026).
A5: Sample | B5: Both reviews tested (100%).
A6: Test attributes | B6: A) Review completed by the due date. B) Performed by the system owner. C) User list was complete (agreed to system extract). D) Flagged accounts removed within 5 business days.
A8: Quarter | B8: Due date | C8: Completed | D8: Reviewer | E8: User list complete? | F8: Accounts reviewed | G8: Accounts flagged | H8: Flagged access removed | I8: On time? | J8: Business days to removal | K8: Result
A9: Q1 2026 | B9: 46127 | C9: 46121 | D9: System owner (Head of Payments Ops) | E9: Yes | F9: 214 | G9: 3 | H9: 46126 | I9: =IF(C9<=B9,"Yes","No") -> Yes | J9: =NETWORKDAYS(C9,H9)-1 -> 3 | K9: =IF(AND(I9="Yes",E9="Yes",J9<=5),"Pass","Exception") -> Pass
A10: Q2 2026 | B10: 46218 | C10: 46211 | D10: System owner (Head of Payments Ops) | E10: Yes | F10: 221 | G10: 2 | H10: 46213 | I10: =IF(C10<=B10,"Yes","No") -> Yes | J10: =NETWORKDAYS(C10,H10)-1 -> 2 | K10: =IF(AND(I10="Yes",E10="Yes",J10<=5),"Pass","Exception") -> Pass

Sheet CM-01 Changes
A1: CM-01 Change approval and testing before deployment
A3: Control | B3: Every change to LedgerCore is logged in the ticketing tool, tested in UAT, and approved by the Change Advisory Board (CAB) before the Release team deploys it. Emergency changes need documented CTO approval before deployment.
A4: Population | B4: 60 production changes between 1 Jan and 30 Jun 2026 (ticketing tool export, agreed to the deployment log for completeness).
A5: Sample | B5: 15 changes selected at random, including 2 emergency changes.
A6: Test attributes | B6: A) UAT evidence exists. B) Approval dated on or before deployment. C) Deployed by the Release team, not the developer.
A8: Change ID | B8: Description | C8: Type | D8: UAT evidence? | E8: Approval date | F8: Deployment date | G8: Deployed by | H8: Approved before deployment? | I8: Result
A9: CHG-1004 | B9: Fix rounding error in FX fee calculation | C9: Standard | D9: Yes | E9: 46029 | F9: 46030 | G9: Release team | H9: =IF(E9<=F9,"Yes","No") -> Yes | I9: =IF(AND(D9="Yes",H9="Yes",G9="Release team"),"Pass","Exception") -> Pass
A10: CHG-1011 | B10: Add IBAN validation to payee set-up | C10: Standard | D10: Yes | E10: 46042 | F10: 46044 | G10: Release team | H10: =IF(E10<=F10,"Yes","No") -> Yes | I10: =IF(AND(D10="Yes",H10="Yes",G10="Release team"),"Pass","Exception") -> Pass
A11: CHG-1016 | B11: Upgrade payment API library | C11: Standard | D11: Yes | E11: 46056 | F11: 46058 | G11: Release team | H11: =IF(E11<=F11,"Yes","No") -> Yes | I11: =IF(AND(D11="Yes",H11="Yes",G11="Release team"),"Pass","Exception") -> Pass
A12: CHG-1020 | B12: Update monthly invoice PDF template | C12: Standard | D12: Yes | E12: 46065 | F12: 46065 | G12: Release team | H12: =IF(E12<=F12,"Yes","No") -> Yes | I12: =IF(AND(D12="Yes",H12="Yes",G12="Release team"),"Pass","Exception") -> Pass
A13: CHG-1024 | B13: Database index for settlement reports | C13: Standard | D13: Yes | E13: 46077 | F13: 46079 | G13: Release team | H13: =IF(E13<=F13,"Yes","No") -> Yes | I13: =IF(AND(D13="Yes",H13="Yes",G13="Release team"),"Pass","Exception") -> Pass
A14: CHG-1029 | B14: New role for Customer Ops refunds | C14: Standard | D14: Yes | E14: 46086 | F14: 46087 | G14: Release team | H14: =IF(E14<=F14,"Yes","No") -> Yes | I14: =IF(AND(D14="Yes",H14="Yes",G14="Release team"),"Pass","Exception") -> Pass
A15: CHG-1033 | B15: Shorten session timeout setting | C15: Standard | D15: Yes | E15: 46099 | F15: 46100 | G15: Release team | H15: =IF(E15<=F15,"Yes","No") -> Yes | I15: =IF(AND(D15="Yes",H15="Yes",G15="Release team"),"Pass","Exception") -> Pass
A16: CHG-1038 | B16: Settlement batch job schedule change | C16: Standard | D16: Yes | E16: 46112 | F16: 46114 | G16: Release team | H16: =IF(E16<=F16,"Yes","No") -> Yes | I16: =IF(AND(D16="Yes",H16="Yes",G16="Release team"),"Pass","Exception") -> Pass
A17: CHG-1047 | B17: Hotfix: duplicate payment notifications | C17: Emergency | D17: Yes | E17: 46128 | F17: 46126 | G17: Release team | H17: =IF(E17<=F17,"Yes","No") -> No | I17: =IF(AND(D17="Yes",H17="Yes",G17="Release team"),"Pass","Exception") -> Exception
A18: CHG-1051 | B18: Add audit log field for refund approvals | C18: Standard | D18: Yes | E18: 46140 | F18: 46142 | G18: Release team | H18: =IF(E18<=F18,"Yes","No") -> Yes | I18: =IF(AND(D18="Yes",H18="Yes",G18="Release team"),"Pass","Exception") -> Pass
A19: CHG-1055 | B19: Update TLS configuration on API gateway | C19: Standard | D19: Yes | E19: 46154 | F19: 46156 | G19: Release team | H19: =IF(E19<=F19,"Yes","No") -> Yes | I19: =IF(AND(D19="Yes",H19="Yes",G19="Release team"),"Pass","Exception") -> Pass
A20: CHG-1060 | B20: Chargeback status dashboard | C20: Standard | D20: Yes | E20: 46163 | F20: 46168 | G20: Release team | H20: =IF(E20<=F20,"Yes","No") -> Yes | I20: =IF(AND(D20="Yes",H20="Yes",G20="Release team"),"Pass","Exception") -> Pass
... A23: CHG-1072 | B23: Reconciliation report column change | C23: Standard | D23: Yes | E23: 46198 | F23: 46202 | G23: Release team | H23: =IF(E23<=F23,"Yes","No") -> Yes | I23: =IF(AND(D23="Yes",H23="Yes",G23="Release team"),"Pass","Exception") -> Pass
A25: Note: CHG-1047 was deployed 2 days before approval, with no documented emergency justification (EX-02). CHG-1064 shows an emergency change handled correctly.

Sheet CM-02 SoD
A1: CM-02 Segregation of duties: developers cannot deploy to production
A3: Control | B3: Only Release and DevOps staff hold production deployment rights in the CI/CD pipeline, and every deployment needs a second approver. Developers cannot deploy their own code.
A4: Population | B4: 6 accounts with production deployment rights (pipeline permission export, 30 Jun 2026).
A5: Sample | B5: All 6 accounts tested (100%). Pipeline configuration inspected: second approver is enforced (Yes).
A6: Test attributes | B6: A) Account holder's role (per HR) is in Release or DevOps. B) Account holder is not in the development team.
A8: Account | B8: Role per HR | C8: Team | D8: Release / DevOps role? | E8: In development team? | F8: Result
A9: usr_rel01 | B9: Release Engineer | C9: Release | D9: Yes | E9: No | F9: =IF(AND(D9="Yes",E9="No"),"Pass","Exception") -> Pass
A10: usr_rel02 | B10: Release Engineer | C10: Release | D10: Yes | E10: No | F10: =IF(AND(D10="Yes",E10="No"),"Pass","Exception") -> Pass
A11: usr_ops01 | B11: DevOps Engineer | C11: DevOps | D11: Yes | E11: No | F11: =IF(AND(D11="Yes",E11="No"),"Pass","Exception") -> Pass
A12: usr_ops02 | B12: DevOps Engineer | C12: DevOps | D12: Yes | E12: No | F12: =IF(AND(D12="Yes",E12="No"),"Pass","Exception") -> Pass
A13: usr_rel03 | B13: Release Manager | C13: Release | D13: Yes | E13: No | F13: =IF(AND(D13="Yes",E13="No"),"Pass","Exception") -> Pass
A14: svc_pipeline | B14: Service account (owner: Release Manager) | C14: Release | D14: Yes | E14: No | F14: =IF(AND(D14="Yes",E14="No"),"Pass","Exception") -> Pass

Sheet OP-01 Backups
A1: OP-01 Daily backup monitoring and failure resolution
A3: Control | B3: The production database is backed up automatically every day. Failed backups raise an alert, and the Infrastructure team logs a ticket and re-runs the backup successfully within 24 hours.
A4: Population | B4: 181 daily backup jobs between 1 Jan and 30 Jun 2026 (backup tool job history).
A5: Sample | B5: 25 days selected at random.
A6: Test attributes | B6: A) Backup succeeded, OR B) if it failed: alert raised, ticket logged, and successful re-run within 24 hours.
A8: Backup date | B8: Job status | C8: Alert raised? | D8: Ticket | E8: Successful re-run within 24h? | F8: Result
A9: 46028 | B9: Success | C9: N/A | D9: N/A | E9: N/A | F9: =IF(B9="Success","Pass",IF(AND(C9="Yes",E9="Yes"),"Pass","Exception")) -> Pass
A10: 46036 | B10: Success | C10: N/A | D10: N/A | E10: N/A | F10: =IF(B10="Success","Pass",IF(AND(C10="Yes",E10="Yes"),"Pass","Exception")) -> Pass
A11: 46043 | B11: Success | C11: N/A | D11: N/A | E11: N/A | F11: =IF(B11="Success","Pass",IF(AND(C11="Yes",E11="Yes"),"Pass","Exception")) -> Pass
A12: 46051 | B12: Success | C12: N/A | D12: N/A | E12: N/A | F12: =IF(B12="Success","Pass",IF(AND(C12="Yes",E12="Yes"),"Pass","Exception")) -> Pass
A13: 46057 | B13: Success | C13: N/A | D13: N/A | E13: N/A | F13: =IF(B13="Success","Pass",IF(AND(C13="Yes",E13="Yes"),"Pass","Exception")) -> Pass
A14: 46064 | B14: Success | C14: N/A | D14: N/A | E14: N/A | F14: =IF(B14="Success","Pass",IF(AND(C14="Yes",E14="Yes"),"Pass","Exception")) -> Pass
A15: 46072 | B15: Success | C15: N/A | D15: N/A | E15: N/A | F15: =IF(B15="Success","Pass",IF(AND(C15="Yes",E15="Yes"),"Pass","Exception")) -> Pass
A16: 46078 | B16: Success | C16: N/A | D16: N/A | E16: N/A | F16: =IF(B16="Success","Pass",IF(AND(C16="Yes",E16="Yes"),"Pass","Exception")) -> Pass
A17: 46085 | B17: Success | C17: N/A | D17: N/A | E17: N/A | F17: =IF(B17="Success","Pass",IF(AND(C17="Yes",E17="Yes"),"Pass","Exception")) -> Pass
A18: 46091 | B18: Failed | C18: Yes | D18: INC-2210 | E18: Yes | F18: =IF(B18="Success","Pass",IF(AND(C18="Yes",E18="Yes"),"Pass","Exception")) -> Pass
A19: 46099 | B19: Success | C19: N/A | D19: N/A | E19: N/A | F19: =IF(B19="Success","Pass",IF(AND(C19="Yes",E19="Yes"),"Pass","Exception")) -> Pass
A20: 46107 | B20: Success | C20: N/A | D20: N/A | E20: N/A | F20: =IF(B20="Success","Pass",IF(AND(C20="Yes",E20="Yes"),"Pass","Exception")) -> Pass
... A33: 46198 | B33: Success | C33: N/A | D33: N/A | E33: N/A | F33: =IF(B33="Success","Pass",IF(AND(C33="Yes",E33="Yes"),"Pass","Exception")) -> Pass
A35: Note: 2 failed backups in the sample were alerted, ticketed and re-run successfully the same day, so the control worked as designed.

Sheet OP-02 Restore Tests
A1: OP-02 Quarterly backup restoration testing
A3: Control | B3: Each quarter the Infrastructure team restores the production database to a test environment, checks data integrity, and records the time taken against the 4-hour recovery time objective (RTO).
A4: Population | B4: 2 quarterly restore tests (Q1 and Q2 2026).
A5: Sample | B5: Both tests (100%).
A6: Test attributes | B6: A) Restore succeeded. B) Data integrity check performed. C) Restore time within the RTO.
A8: Quarter | B8: Test date | C8: System restored | D8: Restore successful? | E8: Integrity check done? | F8: RTO target (hours) | G8: Actual time (hours) | H8: Within RTO? | I8: Result
A9: Q1 2026 | B9: 46099 | C9: LedgerCore production database | D9: Yes | E9: Yes | F9: 4 | G9: 2.7 | H9: =IF(G9<=F9,"Yes","No") -> Yes | I9: =IF(AND(D9="Yes",E9="Yes",H9="Yes"),"Pass","Exception") -> Pass
A10: Q2 2026 | B10: 46190 | C10: LedgerCore production database | D10: Yes | E10: Yes | F10: 4 | G10: 3.1 | H10: =IF(G10<=F10,"Yes","No") -> Yes | I10: =IF(AND(D10="Yes",E10="Yes",H10="Yes"),"Pass","Exception") -> Pass

Sheet Exceptions
A1: Exceptions Log
A2: Management responses are simulated for this portfolio project.
A4: Ref | B4: Control | C4: What we found | D4: Root cause | E4: Risk | F4: Mitigating factors | G4: Rating | H4: Recommendation | I4: Management response (simulated) | J4: Owner | K4: Target date
A5: EX-01 | B5: AC-01 | C5: 1 of 10 leavers (E1019) kept LedgerCore access for 8 business days after leaving. | D5: Leaver ticket was assigned to a Service Desk queue that was not monitored during a staff absence. | E5: A former employee could have accessed or changed financial data. | F5: System logs show no log-ins after termination. User held read-only Sales access. | G5: Medium | H5: Automate access removal from the HR leaver feed, or add a daily check of unactioned leaver tickets. | I5: Agreed. Daily leaver ticket check introduced; automated HR feed in the Q4 roadmap. | J5: IT Service Desk Lead | K5: 46326
A6: EX-02 | B6: CM-01 | C6: 1 of 15 changes (CHG-1047, emergency hotfix) was deployed 2 days before approval, with no documented emergency justification. | D6: Emergency process was followed verbally out of hours; approval and justification were not recorded at the time. | E6: Unapproved changes could introduce errors into payment calculations without oversight. | F6: Retrospective CAB review found the change worked as intended; no adverse impact identified. | G6: Medium | H6: Require documented CTO approval in the ticket before any emergency deployment, and review all emergency changes at the next CAB. | I6: Agreed. Ticket workflow updated to block emergency deployment without recorded approval. | J6: Change Manager | K6: 46295
A8: Rating key | B8: High: control failure could directly cause a material error or breach, no mitigation. Medium: real weakness, but limited impact or mitigating factors exist. Low: minor process or documentation gap.

Sheet Framework Mapping
A1: Framework Mapping
A2: Indicative mapping for learning purposes. Always confirm against the source text.
A4: Control | B4: ISO 27001:2022 Annex A | C4: DORA (Regulation (EU) 2022/2554) | D4: SOC 2 Trust Services Criteria (2017) | E4: Why it matters
A5: AC-01 Leaver access | B5: A.5.18 Access rights; A.6.5 Responsibilities after termination or change of employment | C5: Art. 9(4)(c) access policies and administration of access rights | D5: CC6.2, CC6.3 | E5: Stops former staff using old accounts
A6: AC-02 Access review | B6: A.5.18 Access rights; A.8.2 Privileged access rights | C6: Art. 9(4)(c); further detailed in the RTS on ICT risk management (Delegated Regulation (EU) 2024/1774) | D6: CC6.2, CC6.3 | E6: Catches access that has built up or is no longer needed
A7: CM-01 Change approval | B7: A.8.32 Change management; A.8.29 Security testing in development and acceptance | C7: Art. 9(4)(e) ICT change management | D7: CC8.1 | E7: Prevents untested or unauthorised changes to financial calculations
A8: CM-02 Segregation of duties | B8: A.5.3 Segregation of duties; A.8.31 Separation of development, test and production environments | C8: Art. 9(4)(c) and (e) | D8: CC8.1 | E8: No one person can write and release code on their own
A9: OP-01 Backup monitoring | B9: A.8.13 Information backup; A.8.16 Monitoring activities | C9: Art. 12 backup policies, restoration and recovery | D9: A1.2 | E9: Makes sure data can be recovered
A10: OP-02 Restore testing | B10: A.8.13 Information backup; A.5.30 ICT readiness for business continuity | C10: Art. 12; Art. 11 response and recovery | D10: A1.3 | E10: Proves backups work before they are needed
