Workbook

Sheet 1. Assessment Overview
A1: NIS2 Gap Assessment — HealthNet Ireland Ltd
A2: Directive (EU) 2022/2555 | Assessment date: July 2026 | Assessor: GRC Analyst | Status: Final Draft v1.0
A4: COMPANY PROFILE
A5: Company | B5: HealthNet Ireland Ltd (fictional entity for portfolio purposes)
A6: Location | B6: Dublin, Ireland
A7: Headcount / Turnover | B7: 200 employees / approx. €30M annual turnover — still a MEDIUM-sized enterprise per EU Recommendation 2003/361/EC (large = 250+ staff or >€50M turnover)
A8: Business | B8: Cloud-based patient management and e-referral SaaS platform; managed ICT services to Irish hospitals and GP clinics
A9: Key dependencies | B9: AWS (eu-west-1, Dublin) hosting; HSE integration endpoints; 3 critical software suppliers
A11: NIS2 CLASSIFICATION
A12: Sector | B12: ICT service management (B2B) — Annex I, Sector 8 (managed service provider); services critical to the health sector (Annex I, Sector 5 customers)
A13: Entity type | B13: IMPORTANT ENTITY — Annex I sector but medium-sized (200 staff / €30M is below the 250 staff / €50M large-enterprise threshold), therefore not an essential entity under Art. 3
A14: Classification rationale | B14: Sector determines scope; size determines essential vs important. As an important entity HealthNet faces ex-post supervision (Art. 33) and fines up to €7M or 1.4% of worldwide turnover (Art. 34(5)), but the Art. 21 security measures and Art. 23 reporting obligations apply in full.
A15: Competent authority (IE) | B15: NCSC Ireland (lead competent authority); ComReg designated for ICT service management sector under the draft National Cyber Security Bill. CSIRT-IE receives incident notifications.
A16: Irish transposition status | B16: National Cyber Security Bill (General Scheme published 30 Aug 2024) progressing through the Oireachtas as of mid-2026; EU transposition deadline of 17 Oct 2024 missed and infringement proceedings opened. Directive obligations should be treated as imminent; NCSC guidance (incl. draft Risk Management Measures and the CyFun framework) already published.
A18: SCOPE & METHODOLOGY
A19: Scope | B19: All information systems supporting the SaaS platform, managed services operation, and corporate IT. Assessed against Art. 20 (governance), Art. 21(2)(a)-(j) (risk management measures), Art. 23 (incident reporting) and registration obligations.
A20: Method | B20: Requirements decomposed into 51 assessable statements. Evidence gathered via (simulated) document review, staff interviews and technical configuration review. Each requirement rated for conformance and residual risk.
A21: Rating scale | B21: Compliant = requirement fully met with evidence | Partially Compliant = measure exists but incomplete, informal or unevidenced | Non-Compliant = no meaningful measure in place
A22: Risk rating | B22: High = gap exposes HealthNet to significant regulatory, operational or patient-safety impact | Medium = material weakness, compensating controls exist | Low = minor / documentation-level gap
A24: RELATED PROJECTS
A25: Cross-reference | B25: ISO 27001:2022 ISMS pack (Project 1, TechBridge Solutions) — ISO 27001 is increasingly recognised across the EU as the foundation for evidencing NIS2 compliance; control references included in the remediation roadmap.

Sheet 2. Gap Assessment
A1: NIS2 Gap Assessment Register — HealthNet Ireland Ltd
A2: 51 requirements decomposed from Art. 20, Art. 21(2)(a)-(j), Art. 23 and registration obligations
A4: Ref | B4: NIS2 Article | C4: Domain | D4: Requirement | E4: Current State (Evidence Observed) | F4: Status | G4: Risk | H4: Gap Description
A5: GOV-01 | B5: Art. 20(1) | C5: Governance & Accountability | D5: Management board formally approves the cybersecurity risk-management measures. | E5: Cybersecurity is delegated entirely to the IT Manager; the board has never formally approved the risk-management measures or recorded such approval in minutes. | F5: Non-Compliant | G5: High | H5: No documented board approval. Under the Irish NCSB General Scheme (Head 28) and Head 43 personal liability provisions, directors face direct exposure.
A6: GOV-02 | B6: Art. 20(1) | C6: Governance & Accountability | D6: Management board oversees implementation of the measures and can be held accountable. | E6: Quarterly IT report to the board covers uptime and budget only; no cyber risk KPIs or oversight mechanism. | F6: Non-Compliant | G6: High | H6: No board-level oversight of cyber risk; no cyber items on standing board agenda.
A7: GOV-03 | B7: Art. 20(2) | C7: Governance & Accountability | D7: Members of the management board follow cybersecurity training. | E7: CEO attended one NCSC webinar in 2025; no structured board training programme. | F7: Partially Compliant | G7: Medium | H7: Ad-hoc awareness only; no regular, documented board training as required.
A8: GOV-04 | B8: Art. 20(2) | C8: Governance & Accountability | D8: Equivalent training is offered to employees on a regular basis. | E8: Annual security e-learning assigned to all staff; 78% completion rate, no follow-up for non-completers. | F8: Partially Compliant | G8: Medium | H8: Training exists but completion is not enforced or role-tailored.
A9: RSK-01 | B9: Art. 21(2)(a) | C9: Risk Analysis & Policies | D9: A documented information security policy exists, approved by management. | E9: Information Security Policy v2.1 exists, signed by the CEO in 2024, but not reviewed since. | F9: Partially Compliant | G9: Low | H9: Policy overdue for annual review; no defined review cycle.
A10: RSK-02 | B10: Art. 21(2)(a) | C10: Risk Analysis & Policies | D10: A formal, repeatable risk assessment methodology is defined and applied. | E10: Risks discussed informally at IT team meetings; no methodology, criteria or risk register. | F10: Non-Compliant | G10: High | H10: No risk assessment process — the foundational Art. 21 requirement. All other measures should be proportionate to assessed risk.
A11: RSK-03 | B11: Art. 21(2)(a) | C11: Risk Analysis & Policies | D11: A maintained risk register with owners, scores and treatment decisions exists. | E11: No risk register exists. | F11: Non-Compliant | G11: High | H11: No visibility of the organisation's risk position; nothing to evidence 'proportionality' to a regulator.
A12: RSK-04 | B12: Art. 21(2)(a) | C12: Risk Analysis & Policies | D12: An all-hazards approach is taken (physical, environmental and cyber threats considered). | E12: Assessments (informal) consider cyber threats only; physical security of the office server room never reviewed. | F12: Non-Compliant | G12: Medium | H12: NIS2 Art. 21(1) explicitly requires an all-hazards approach including physical resilience.
A13: INC-01 | B13: Art. 21(2)(b) | C13: Incident Handling | D13: A documented incident response plan/procedure exists. | E13: No incident response plan or procedure of any kind; staff would improvise if an attack occurred. | F13: Non-Compliant | G13: High | H13: No IR plan at all: no severity classification (P1-P4), no roles, no playbooks. In a real incident, decisions would be made under panic with no structure.
A14: INC-02 | B14: Art. 21(2)(b) | C14: Incident Handling | D14: Incidents are detected, logged and tracked through to resolution. | E14: Helpdesk tickets capture some incidents; no central security incident log; no SIEM. | F14: Partially Compliant | G14: High | H14: Detection capability limited to endpoint AV alerts; no centralised logging or monitoring of the SaaS platform.
A15: INC-03 | B15: Art. 21(2)(b) | C15: Incident Handling | D15: Roles and responsibilities during an incident are defined (incl. out-of-hours). | E15: IT Manager is the single point of contact; no deputy, no out-of-hours rota. | F15: Non-Compliant | G15: Medium | H15: Single point of failure for incident command; no 24/7 contact path despite hospital customers operating 24/7.
... A55: REG-02 | B55: NCSB / NCSC | C55: Registration & Regulator Engagement | D55: Monitoring of Irish transposition (National Cyber Security Bill) and NCSC guidance (RMM, CyFun). | E55: No one is assigned to track regulatory developments. | F55: Non-Compliant | G55: Low | H55: Assign ownership for horizon-scanning; NCSC draft Risk Management Measures and CyFun already signal expected controls.

Sheet 3. Remediation Roadmap
A1: Remediation Roadmap — HealthNet Ireland Ltd
A2: Prioritised actions for all Partially/Non-Compliant findings | P1 = 0-3 months, P2 = 3-6 months, P3 = 6-12 months
A4: Ref | B4: Remediation Action | C4: ISO 27001:2022 Ref | D4: Owner | E4: Priority | F4: Effort | G4: Target
A5: GOV-01 | B5: Present risk-management measures to the board for formal approval; record in minutes. Establish standing quarterly cyber agenda item. | C5: Clause 5.1 | D5: CEO / Board | E5: P1 | F5: Low | G5: Q3 2026
A6: GOV-02 | B6: Define board cyber-risk dashboard (top risks, incidents, training %, patching SLA) reported quarterly. | C6: Clause 9.3 | D6: IT Manager | E6: P1 | F6: Low | G6: Q3 2026
A7: RSK-02 | B7: Adopt a risk assessment methodology (ISO 27005-aligned, 5x5 likelihood x impact); run first full assessment covering cyber, physical and supply-chain (all-hazards). | C7: Clause 6.1.2 | D7: IT Manager | E7: P1 | F7: Medium | G7: Q3 2026
A8: RSK-03 | B8: Establish risk register with owners, scores, treatment decisions; review quarterly. | C8: Clause 6.1.3 | D8: IT Manager | E8: P1 | F8: Low | G8: Q3 2026
A9: REP-01 | B9: Create NIS2 incident reporting procedure: significance criteria, 24h early warning template, 72h notification template, 1-month final report template; record CSIRT-IE contact details; brief on-call staff. Align with (but keep distinct from) GDPR Art. 33 process. | C9: A.5.24 / A.5.5 | D9: IT Manager + DPO | E9: P1 | F9: Medium | G9: Q3 2026
A10: MFA-01 | B10: Enforce MFA on AWS console (IAM policy) and SaaS admin portal immediately. | C10: A.5.17 / A.8.5 | D10: Platform Lead | E10: P1 | F10: Low | G10: Q3 2026
A11: BCM-02 | B11: Implement immutable/offline backup copy (e.g. S3 Object Lock in separate account); schedule quarterly restore tests. | C11: A.8.13 | D11: Platform Lead | E11: P1 | F11: Medium | G11: Q3 2026
A12: HRA-01 | B12: Formalise JML process: HR-triggered leaver checklist with same-day access revocation; immediate audit and removal of orphaned accounts. | C12: A.6.1-A.6.5 / A.5.18 | D12: HR + IT | E12: P1 | F12: Low | G12: Q3 2026
A13: CRY-03 | B13: Deploy secrets management (e.g. AWS Secrets Manager); purge hardcoded secrets from repos; define rotation schedule. | C13: A.8.24 | D13: Platform Lead | E13: P1 | F13: Medium | G13: Q4 2026
A14: INC-01 | B14: Develop full incident response plan: P1-P4 severity model, roles incl. deputy IR lead, ransomware and data-breach playbooks, out-of-hours contact rota. | C14: A.5.24-A.5.28 | D14: IT Manager | E14: P2 | F14: Medium | G14: Q4 2026
A15: INC-02 | B15: Centralise security logging for platform and corporate estate (cloud-native SIEM tier acceptable at current scale); define alerting use cases. | C15: A.8.15 / A.8.16 | D15: Platform Lead | E15: P2 | F15: High | G15: Q1 2027
... A37: REG-01 | B37: Prepare registration pack (entity details, contacts, sector, member states served) ready for submission when the Irish NIS2 portal opens; assign regulatory horizon-scanning owner (also covers REG-02). | C37: A.5.31 | D37: DPO | E37: P2 | F37: Low | G37: Q4 2026

Sheet 4. Executive Dashboard
A1: Executive Dashboard — NIS2 Readiness
A2: All figures calculated live from Sheet '2. Gap Assessment' — updates automatically as statuses change
A4: OVERALL POSITION
A5: Total requirements assessed | B5: =COUNTA('2. Gap Assessment'!$A$5:$A$55) -> 51
A6: Compliant | B6: =COUNTIF('2. Gap Assessment'!$F$5:$F$55,"Compliant") -> 2
A7: Partially Compliant | B7: =COUNTIF('2. Gap Assessment'!$F$5:$F$55,"Partially Compliant") -> 19
A8: Non-Compliant | B8: =COUNTIF('2. Gap Assessment'!$F$5:$F$55,"Non-Compliant") -> 30
A9: Overall compliance score (Compliant + 0.5 x Partial) | B9: =(COUNTIF('2. Gap Assessment'!$F$5:$F$55,"Compliant")+0.5*COUNTIF('2. Gap Assessment'!$F$5:$F$55,"Partially Compliant"))/COUNTA('2. Gap Assessment'!$A$5:$A$55) -> 0.2254902
A10: High-risk gaps | B10: =COUNTIF('2. Gap Assessment'!$G$5:$G$55,"High") -> 16
A12: POSITION BY DOMAIN
A13: Domain (NIS2 Article) | B13: Requirements | C13: Compliant | D13: Partial | E13: Non-Compliant | F13: High Risks
A14: Governance & Accountability | B14: =COUNTIF('2. Gap Assessment'!$C$5:$C$55,A14) -> 4 | C14: =COUNTIFS('2. Gap Assessment'!$C$5:$C$55,A14,'2. Gap Assessment'!$F$5:$F$55,"Compliant") -> 0 | D14: =COUNTIFS('2. Gap Assessment'!$C$5:$C$55,A14,'2. Gap Assessment'!$F$5:$F$55,"Partially Compliant") -> 2 | E14: =COUNTIFS('2. Gap Assessment'!$C$5:$C$55,A14,'2. Gap Assessment'!$F$5:$F$55,"Non-Compliant") -> 2 | F14: =COUNTIFS('2. Gap Assessment'!$C$5:$C$55,A14,'2. Gap Assessment'!$G$5:$G$55,"High") -> 2
A15: Risk Analysis & Policies | B15: =COUNTIF('2. Gap Assessment'!$C$5:$C$55,A15) -> 4 | C15: =COUNTIFS('2. Gap Assessment'!$C$5:$C$55,A15,'2. Gap Assessment'!$F$5:$F$55,"Compliant") -> 0 | D15: =COUNTIFS('2. Gap Assessment'!$C$5:$C$55,A15,'2. Gap Assessment'!$F$5:$F$55,"Partially Compliant") -> 1 | E15: =COUNTIFS('2. Gap Assessment'!$C$5:$C$55,A15,'2. Gap Assessment'!$F$5:$F$55,"Non-Compliant") -> 3 | F15: =COUNTIFS('2. Gap Assessment'!$C$5:$C$55,A15,'2. Gap Assessment'!$G$5:$G$55,"High") -> 2
A16: Incident Handling | B16: =COUNTIF('2. Gap Assessment'!$C$5:$C$55,A16) -> 5 | C16: =COUNTIFS('2. Gap Assessment'!$C$5:$C$55,A16,'2. Gap Assessment'!$F$5:$F$55,"Compliant") -> 0 | D16: =COUNTIFS('2. Gap Assessment'!$C$5:$C$55,A16,'2. Gap Assessment'!$F$5:$F$55,"Partially Compliant") -> 1 | E16: =COUNTIFS('2. Gap Assessment'!$C$5:$C$55,A16,'2. Gap Assessment'!$F$5:$F$55,"Non-Compliant") -> 4 | F16: =COUNTIFS('2. Gap Assessment'!$C$5:$C$55,A16,'2. Gap Assessment'!$G$5:$G$55,"High") -> 2
A17: Business Continuity & Backup | B17: =COUNTIF('2. Gap Assessment'!$C$5:$C$55,A17) -> 5 | C17: =COUNTIFS('2. Gap Assessment'!$C$5:$C$55,A17,'2. Gap Assessment'!$F$5:$F$55,"Compliant") -> 1 | D17: =COUNTIFS('2. Gap Assessment'!$C$5:$C$55,A17,'2. Gap Assessment'!$F$5:$F$55,"Partially Compliant") -> 1 | E17: =COUNTIFS('2. Gap Assessment'!$C$5:$C$55,A17,'2. Gap Assessment'!$F$5:$F$55,"Non-Compliant") -> 3 | F17: =COUNTIFS('2. Gap Assessment'!$C$5:$C$55,A17,'2. Gap Assessment'!$G$5:$G$55,"High") -> 2
A18: Supply Chain Security | B18: =COUNTIF('2. Gap Assessment'!$C$5:$C$55,A18) -> 4 | C18: =COUNTIFS('2. Gap Assessment'!$C$5:$C$55,A18,'2. Gap Assessment'!$F$5:$F$55,"Compliant") -> 0 | D18: =COUNTIFS('2. Gap Assessment'!$C$5:$C$55,A18,'2. Gap Assessment'!$F$5:$F$55,"Partially Compliant") -> 1 | E18: =COUNTIFS('2. Gap Assessment'!$C$5:$C$55,A18,'2. Gap Assessment'!$F$5:$F$55,"Non-Compliant") -> 3 | F18: =COUNTIFS('2. Gap Assessment'!$C$5:$C$55,A18,'2. Gap Assessment'!$G$5:$G$55,"High") -> 1
A19: Secure Development & Vulnerability Handling | B19: =COUNTIF('2. Gap Assessment'!$C$5:$C$55,A19) -> 4 | C19: =COUNTIFS('2. Gap Assessment'!$C$5:$C$55,A19,'2. Gap Assessment'!$F$5:$F$55,"Compliant") -> 0 | D19: =COUNTIFS('2. Gap Assessment'!$C$5:$C$55,A19,'2. Gap Assessment'!$F$5:$F$55,"Partially Compliant") -> 3 | E19: =COUNTIFS('2. Gap Assessment'!$C$5:$C$55,A19,'2. Gap Assessment'!$F$5:$F$55,"Non-Compliant") -> 1 | F19: =COUNTIFS('2. Gap Assessment'!$C$5:$C$55,A19,'2. Gap Assessment'!$G$5:$G$55,"High") -> 1
A20: Effectiveness Assessment | B20: =COUNTIF('2. Gap Assessment'!$C$5:$C$55,A20) -> 3 | C20: =COUNTIFS('2. Gap Assessment'!$C$5:$C$55,A20,'2. Gap Assessment'!$F$5:$F$55,"Compliant") -> 0 | D20: =COUNTIFS('2. Gap Assessment'!$C$5:$C$55,A20,'2. Gap Assessment'!$F$5:$F$55,"Partially Compliant") -> 0 | E20: =COUNTIFS('2. Gap Assessment'!$C$5:$C$55,A20,'2. Gap Assessment'!$F$5:$F$55,"Non-Compliant") -> 3 | F20: =COUNTIFS('2. Gap Assessment'!$C$5:$C$55,A20,'2. Gap Assessment'!$G$5:$G$55,"High") -> 0
A21: Cyber Hygiene & Training | B21: =COUNTIF('2. Gap Assessment'!$C$5:$C$55,A21) -> 4 | C21: =COUNTIFS('2. Gap Assessment'!$C$5:$C$55,A21,'2. Gap Assessment'!$F$5:$F$55,"Compliant") -> 0 | D21: =COUNTIFS('2. Gap Assessment'!$C$5:$C$55,A21,'2. Gap Assessment'!$F$5:$F$55,"Partially Compliant") -> 3 | E21: =COUNTIFS('2. Gap Assessment'!$C$5:$C$55,A21,'2. Gap Assessment'!$F$5:$F$55,"Non-Compliant") -> 1 | F21: =COUNTIFS('2. Gap Assessment'!$C$5:$C$55,A21,'2. Gap Assessment'!$G$5:$G$55,"High") -> 0
A22: Cryptography | B22: =COUNTIF('2. Gap Assessment'!$C$5:$C$55,A22) -> 3 | C22: =COUNTIFS('2. Gap Assessment'!$C$5:$C$55,A22,'2. Gap Assessment'!$F$5:$F$55,"Compliant") -> 1 | D22: =COUNTIFS('2. Gap Assessment'!$C$5:$C$55,A22,'2. Gap Assessment'!$F$5:$F$55,"Partially Compliant") -> 1 | E22: =COUNTIFS('2. Gap Assessment'!$C$5:$C$55,A22,'2. Gap Assessment'!$F$5:$F$55,"Non-Compliant") -> 1 | F22: =COUNTIFS('2. Gap Assessment'!$C$5:$C$55,A22,'2. Gap Assessment'!$G$5:$G$55,"High") -> 1
A23: HR, Access Control & Assets | B23: =COUNTIF('2. Gap Assessment'!$C$5:$C$55,A23) -> 5 | C23: =COUNTIFS('2. Gap Assessment'!$C$5:$C$55,A23,'2. Gap Assessment'!$F$5:$F$55,"Compliant") -> 0 | D23: =COUNTIFS('2. Gap Assessment'!$C$5:$C$55,A23,'2. Gap Assessment'!$F$5:$F$55,"Partially Compliant") -> 3 | E23: =COUNTIFS('2. Gap Assessment'!$C$5:$C$55,A23,'2. Gap Assessment'!$F$5:$F$55,"Non-Compliant") -> 2 | F23: =COUNTIFS('2. Gap Assessment'!$C$5:$C$55,A23,'2. Gap Assessment'!$G$5:$G$55,"High") -> 2
A24: Authentication & Secure Comms | B24: =COUNTIF('2. Gap Assessment'!$C$5:$C$55,A24) -> 4 | C24: =COUNTIFS('2. Gap Assessment'!$C$5:$C$55,A24,'2. Gap Assessment'!$F$5:$F$55,"Compliant") -> 0 | D24: =COUNTIFS('2. Gap Assessment'!$C$5:$C$55,A24,'2. Gap Assessment'!$F$5:$F$55,"Partially Compliant") -> 3 | E24: =COUNTIFS('2. Gap Assessment'!$C$5:$C$55,A24,'2. Gap Assessment'!$F$5:$F$55,"Non-Compliant") -> 1 | F24: =COUNTIFS('2. Gap Assessment'!$C$5:$C$55,A24,'2. Gap Assessment'!$G$5:$G$55,"High") -> 1
A25: Incident Reporting | B25: =COUNTIF('2. Gap Assessment'!$C$5:$C$55,A25) -> 4 | C25: =COUNTIFS('2. Gap Assessment'!$C$5:$C$55,A25,'2. Gap Assessment'!$F$5:$F$55,"Compliant") -> 0 | D25: =COUNTIFS('2. Gap Assessment'!$C$5:$C$55,A25,'2. Gap Assessment'!$F$5:$F$55,"Partially Compliant") -> 0 | E25: =COUNTIFS('2. Gap Assessment'!$C$5:$C$55,A25,'2. Gap Assessment'!$F$5:$F$55,"Non-Compliant") -> 4 | F25: =COUNTIFS('2. Gap Assessment'!$C$5:$C$55,A25,'2. Gap Assessment'!$G$5:$G$55,"High") -> 2
A26: Registration & Regulator Engagement | B26: =COUNTIF('2. Gap Assessment'!$C$5:$C$55,A26) -> 2 | C26: =COUNTIFS('2. Gap Assessment'!$C$5:$C$55,A26,'2. Gap Assessment'!$F$5:$F$55,"Compliant") -> 0 | D26: =COUNTIFS('2. Gap Assessment'!$C$5:$C$55,A26,'2. Gap Assessment'!$F$5:$F$55,"Partially Compliant") -> 0 | E26: =COUNTIFS('2. Gap Assessment'!$C$5:$C$55,A26,'2. Gap Assessment'!$F$5:$F$55,"Non-Compliant") -> 2 | F26: =COUNTIFS('2. Gap Assessment'!$C$5:$C$55,A26,'2. Gap Assessment'!$G$5:$G$55,"High") -> 0
A28: TOP 5 PRIORITY MESSAGES FOR THE BOARD
A29: 1. Governance is the headline gap: the board has never approved or overseen cyber risk measures. Under the draft Irish Bill (Heads 28 & 43) this carries potential personal liability for directors.
A30: 2. HealthNet cannot currently meet the 24-hour / 72-hour / 1-month incident reporting clocks — no procedure, templates or CSIRT-IE contact exists. This is the fastest regulatory exposure to fix.
A31: 3. There is no risk assessment process or risk register — the foundation every other NIS2 measure must be proportionate to. Remediate first; it also directly reuses the ISO 27001 methodology.
A32: 4. Quick wins with outsized impact: enforce MFA on the AWS console and admin portal, revoke orphaned ex-employee accounts, and add an immutable backup copy — all achievable inside 90 days.
A33: 5. Hospital customers are already flowing NIS2 obligations down through contracts. Closing these gaps is a commercial enabler, not just a compliance cost.
